{
    "colormaps": {
        "areas_of_interests": "Tableau10",
        "roles": "Greens"
    },
    "multisampling": 4,
    "segments": {
        "display_dur_sec": 45.0,
        "min_dur_sec": 31.0
    },
    "streamgraph": {
        "bottom": {
            "log_scale": true,
            "source": "movement"
        },
        "top": {
            "log_scale": true,
            "source": "attention"
        }
    },
    "timeline": {
        "mapped_fixations": {
            "merge_threshold_sec": 0.5
        },
        "transcript": {
            "merge_threshold_sec": 1.0
        }
    },
    "video_overlay": {
        "attention": {
            "colormap": "CET_L8"
        },
        "movement": {
            "colormap": "CET_L20"
        }
    }
}